README.rst
setup.py
commentjson/__init__.py
commentjson/commentjson.py
commentjson.egg-info/PKG-INFO
commentjson.egg-info/SOURCES.txt
commentjson.egg-info/dependency_links.txt
commentjson.egg-info/not-zip-safe
commentjson.egg-info/requires.txt
commentjson.egg-info/top_level.txt
commentjson/tests/__init__.py
commentjson/tests/test_commentjson.py
commentjson/tests/test_json/__init__.py
commentjson/tests/test_json/test_decode.py
commentjson/tests/test_json/test_dump.py
commentjson/tests/test_json/test_encode_basestring_ascii.py
commentjson/tests/test_json/test_float.py
commentjson/tests/test_json/test_indent.py
commentjson/tests/test_json/test_pass1.py
commentjson/tests/test_json/test_pass2.py
commentjson/tests/test_json/test_pass3.py
commentjson/tests/test_json/test_recursion.py
commentjson/tests/test_json/test_separators.py
commentjson/tests/test_json/test_unicode.py