Metadata-Version: 1.1
Name: commentjson
Version: 0.8.3
Summary: Add Python and JavaScript style comments in your JSON files.
Home-page: https://github.com/vaidik/commentjson
Author: Vaidik Kapoor
Author-email: kapoor.vaidik@gmail.com
License: UNKNOWN
Platform: UNKNOWN
Classifier: Programming Language :: Python
